[
    {
        "id": 1,
        "recipe": "Pasta Casta",
        "type":"BreakFast",
        "dateInfo":{
            "month":3,
            "day":3,
            "date":30
        }
    },
    {
        "id": 2,
        "recipe": "Beans Soup",
        "type":"Launch",
        "dateInfo":{
            "month":3,
            "day":3,
            "date":30
        }
    },
    {
        "id": 3,
        "recipe": "Spagetti",
        "type":"BreakFast",
        "dateInfo":{
            "month":4,
            "day":4,
            "date":1
        }
    },
    {
        "id": 4,
        "recipe": "Corn Meat",
        "type":"Supper",
        "dateInfo":{
            "month":4,
            "day":4,
            "date":1
        }
    },
    {
        "id": 5,
        "recipe": "Rice and Beans",
        "type":"BreakFast",
        "dateInfo":{
            "month":4,
            "day":5,
            "date":2
        }
    },
    {
        "id": 6,
        "recipe": "Pasta Can",
        "type":"Launch",
        "dateInfo":{
            "month":4,
            "day":5,
            "date":2
        }
    },
    {
        "id": 7,
        "recipe": "Meat Mall",
        "type":"Launch",
        "dateInfo":{
            "month":4,
            "day":6,
            "date":3
        }
    },
    {
        "id": 8,
        "recipe": "Salad Dressing",
        "type":"Supper",
        "dateInfo":{
            "month":4,
            "day":6,
            "date":3
        }
    },
    {
        "id": 9,
        "recipe": "Mayonaise and Bread",
        "type":"Supper",
        "dateInfo":{
            "month":4,
            "day":0,
            "date":4
        }
    },
    {
        "id": 10,
        "recipe": "Bread and Tea",
        "type":"BreakFast",
        "dateInfo":{
            "month":4,
            "day":1,
            "date":5
        }
    },
    {
        "id": 11,
        "recipe": "Okro and Garri",
        "type":"Launch",
        "dateInfo":{
            "month":4,
            "day":2,
            "date":6
        }
    }
]
  